MANIFEST.in
setup.cfg
setup.py
libflip/Actor.py
libflip/Animation.py
libflip/Assets.py
libflip/Globals.py
libflip/Inventory.py
libflip/Level.py
libflip/Maze.py
libflip/Sprite.py
libflip/Statistics.py
libflip/Thing.py
libflip/__init__.py
libflip/api.py
libflip/constants.py
libflip/libflip.py
libflip/utils.py
libflip.egg-info/PKG-INFO
libflip.egg-info/SOURCES.txt
libflip.egg-info/dependency_links.txt
libflip.egg-info/entry_points.txt
libflip.egg-info/requires.txt
libflip.egg-info/top_level.txt