Metadata-Version: 1.0
Name: libflip
Version: 2.0.0
Summary: Fivelines instructional game development platform
Home-page: http://fivelines.io
Author: Fivelines Interactive
Author-email: support@fivelines.io
License: UNKNOWN
Platform: UNKNOWN
